pyubqhash.cpython-38-darwin.so
pyubqhash-0.1.25.dist-info/METADATA
pyubqhash-0.1.25.dist-info/WHEEL
pyubqhash-0.1.25.dist-info/top_level.txt
pyubqhash-0.1.25.dist-info/RECORD
